cron_threads.py
cron_threads-0.1.4.dist-info/LICENSE
cron_threads-0.1.4.dist-info/METADATA
cron_threads-0.1.4.dist-info/WHEEL
cron_threads-0.1.4.dist-info/top_level.txt
cron_threads-0.1.4.dist-info/RECORD
